[
  {
    "fuente": "TikTok",
    "consulta": "museo nacional del ecuador",
    "autor": "arquitrip",
    "texto": "Lo que creo del nuevo museo",
    "url": "https://www.tiktok.com/@arquitrip/video/7660361157944806663",
    "vistas": "18.2K",
    "comentarios": []
  },
  {
    "fuente": "TikTok",
    "consulta": "museo nacional del ecuador",
    "autor": "valentinosinr",
    "texto": "No me gustó la propuesta ganadora del MUNA",
    "url": "https://www.tiktok.com/@valentinosinr/video/7660146644033309972",
    "vistas": "47.5K",
    "comentarios": []
  },
  {
    "fuente": "TikTok",
    "consulta": "museo nacional del ecuador",
    "autor": "ec.teban",
    "texto": "¡El estudio ganador para el nuevo Museo Nacional del Ecuador ya publicó sus análisis y motivos para su diseño! 👀",
    "url": "https://www.tiktok.com/@ec.teban/video/7660669783339273479",
    "vistas": "2149",
    "comentarios": []
  },
  {
    "fuente": "TikTok",
    "consulta": "museo nacional del ecuador",
    "autor": "arq.christell",
    "texto": "Nuevo Museo para Ecuador donde albergará 1.4 millones de bienes patrimoniales",
    "url": "https://www.tiktok.com/@arq.christell/video/7660401023307074834",
    "vistas": "40",
    "comentarios": []
  },
  {
    "fuente": "TikTok",
    "consulta": "museo nacional del ecuador",
    "autor": "bycarlos.arq",
    "texto": "No todos los museos empiezan pensando en las obras. Algunos empiezan entendiendo el lugar donde existen.",
    "url": "https://www.tiktok.com/@bycarlos.arq/video/7662163260552105224",
    "vistas": "3539",
    "comentarios": []
  },
  {
    "fuente": "TikTok",
    "consulta": "museo nacional del ecuador",
    "autor": "ecuador_turismo_",
    "texto": "¿Por qué Ecos del Sol?, Diseño ganador del nuevo Museo Nacional 🇪🇨",
    "url": "https://www.tiktok.com/@ecuador_turismo_/video/7660556696703716628",
    "vistas": "3576",
    "comentarios": []
  },
  {
    "fuente": "TikTok",
    "consulta": "museo nacional del ecuador",
    "autor": "lanaranjaec",
    "texto": "🏛️ Ya hay diseño ganador para el nuevo Museo Nacional del Ecuador... y ha desatado un intenso debate. Mientras el jurado eligió la propuesta \"Ecos del Sol\", muchos usuarios en redes cuestionan su estética y aseguran que otras opciones eran más atractivas.",
    "url": "https://www.tiktok.com/@lanaranjaec/video/7660276980058754322",
    "vistas": "375",
    "comentarios": []
  },
  {
    "fuente": "TikTok",
    "consulta": "museo nacional del ecuador",
    "autor": "latamarch",
    "texto": "¿Puede un muro de hormigón representar al Ecuador?",
    "url": "https://www.tiktok.com/@latamarch/video/7660277948229897479",
    "vistas": "3957",
    "comentarios": []
  },
  {
    "fuente": "TikTok",
    "consulta": "museo nacional del ecuador",
    "autor": "soydanny.arte",
    "texto": "Ecuador acaba de elegir el diseño de su nuevo Museo Nacional. $100 millones. El propio estudio ganador describe su exterior como \"sereno, casi silencioso\" 👀",
    "url": "https://www.tiktok.com/@soydanny.arte/video/7660363203725430036",
    "vistas": "4612",
    "comentarios": []
  },
  {
    "fuente": "TikTok",
    "consulta": "museo nacional del ecuador",
    "autor": "factostiktokec",
    "texto": "MUSEO NACIONAL DEL ECUADOR. ROBERTO LUQUE.",
    "url": "https://www.tiktok.com/@factostiktokec/video/7660636909143657749",
    "vistas": "5596",
    "comentarios": []
  },
  {
    "fuente": "TikTok",
    "consulta": "museo nacional del ecuador",
    "autor": "crmstudio4",
    "texto": "Opinamos 😎 #MuNa #MuseoNacionaldelEcuador",
    "url": "https://www.tiktok.com/@crmstudio4/video/7660683678917430536",
    "vistas": "289",
    "comentarios": []
  },
  {
    "fuente": "TikTok",
    "consulta": "museo nacional del ecuador",
    "autor": "bycarlos.arq",
    "texto": "¿Un museo debe convertirse en un ícono... o en una extensión de la ciudad?",
    "url": "https://www.tiktok.com/@bycarlos.arq/video/7660970950086626567",
    "vistas": "127",
    "comentarios": []
  }
]